[{"index":0,"phase_x":348,"phase_y":2631.4477667681},{"index":1,"phase_x":412,"phase_y":2502.5352103775},{"index":2,"phase_x":457,"phase_y":2407.8438110014},{"index":3,"phase_x":463,"phase_y":2368.8590620001},{"index":4,"phase_x":460,"phase_y":2367.4818461861},{"index":5,"phase_x":447,"phase_y":2402.2689953567},{"index":6,"phase_x":425,"phase_y":2453.0866998533},{"index":7,"phase_x":407,"phase_y":2498.9377708071},{"index":8,"phase_x":385,"phase_y":2535.230721972},{"index":9,"phase_x":366,"phase_y":2577.0815048412},{"index":10,"phase_x":356,"phase_y":2615.6416845967},{"index":11,"phase_x":347,"phase_y":2636.9768814247},{"index":12,"phase_x":341,"phase_y":2658.1689991729},{"index":13,"phase_x":334,"phase_y":2674.3196279727},{"index":14,"phase_x":332,"phase_y":2691.4536447922},{"index":15,"phase_x":332,"phase_y":2695.4132938016},{"index":16,"phase_x":330,"phase_y":2699.5241340783},{"index":17,"phase_x":329,"phase_y":2704.7529368923},{"index":18,"phase_x":329,"phase_y":2707.460792593},{"index":19,"phase_x":329,"phase_y":2707.460792593},{"index":20,"phase_x":329,"phase_y":2707.460792593},{"index":21,"phase_x":329,"phase_y":2707.460792593},{"index":22,"phase_x":329,"phase_y":2707.460792593},{"index":23,"phase_x":329,"phase_y":2707.460792593},{"index":24,"phase_x":329,"phase_y":2707.460792593},{"index":25,"phase_x":329,"phase_y":2707.460792593},{"index":26,"phase_x":329,"phase_y":2707.460792593},{"index":27,"phase_x":329,"phase_y":2707.460792593},{"index":28,"phase_x":329,"phase_y":2707.460792593},{"index":29,"phase_x":329,"phase_y":2707.460792593},{"index":30,"phase_x":329,"phase_y":2707.460792593},{"index":31,"phase_x":329,"phase_y":2707.460792593},{"index":32,"phase_x":329,"phase_y":2707.460792593},{"index":33,"phase_x":329,"phase_y":2707.460792593},{"index":34,"phase_x":329,"phase_y":2707.460792593},{"index":35,"phase_x":329,"phase_y":2707.460792593},{"index":36,"phase_x":329,"phase_y":2707.460792593},{"index":37,"phase_x":329,"phase_y":2707.460792593},{"index":38,"phase_x":329,"phase_y":2707.460792593},{"index":39,"phase_x":329,"phase_y":2707.460792593}]