[{"index":0,"phase_x":130,"phase_y":3412.7462740054},{"index":1,"phase_x":216,"phase_y":3096.9551316913},{"index":2,"phase_x":292,"phase_y":2841.6445575578},{"index":3,"phase_x":349,"phase_y":2693.2944053394},{"index":4,"phase_x":369,"phase_y":2620.3062863338},{"index":5,"phase_x":383,"phase_y":2600.5589996029},{"index":6,"phase_x":395,"phase_y":2595.8723470026},{"index":7,"phase_x":399,"phase_y":2600.657507688},{"index":8,"phase_x":399,"phase_y":2605.3366240791},{"index":9,"phase_x":396,"phase_y":2606.4644908882},{"index":10,"phase_x":400,"phase_y":2616.2555282548},{"index":11,"phase_x":400,"phase_y":2620.387842638},{"index":12,"phase_x":400,"phase_y":2620.387842638},{"index":13,"phase_x":400,"phase_y":2620.387842638},{"index":14,"phase_x":400,"phase_y":2620.387842638},{"index":15,"phase_x":400,"phase_y":2620.387842638},{"index":16,"phase_x":400,"phase_y":2620.387842638},{"index":17,"phase_x":400,"phase_y":2620.387842638},{"index":18,"phase_x":400,"phase_y":2620.387842638},{"index":19,"phase_x":400,"phase_y":2620.387842638},{"index":20,"phase_x":400,"phase_y":2620.387842638},{"index":21,"phase_x":400,"phase_y":2620.387842638},{"index":22,"phase_x":400,"phase_y":2620.387842638},{"index":23,"phase_x":400,"phase_y":2620.387842638},{"index":24,"phase_x":400,"phase_y":2620.387842638},{"index":25,"phase_x":400,"phase_y":2620.387842638},{"index":26,"phase_x":400,"phase_y":2620.387842638},{"index":27,"phase_x":400,"phase_y":2620.387842638},{"index":28,"phase_x":400,"phase_y":2620.387842638},{"index":29,"phase_x":400,"phase_y":2620.387842638},{"index":30,"phase_x":400,"phase_y":2620.387842638},{"index":31,"phase_x":400,"phase_y":2620.387842638},{"index":32,"phase_x":400,"phase_y":2620.387842638},{"index":33,"phase_x":400,"phase_y":2620.387842638},{"index":34,"phase_x":400,"phase_y":2620.387842638},{"index":35,"phase_x":400,"phase_y":2620.387842638},{"index":36,"phase_x":400,"phase_y":2620.387842638},{"index":37,"phase_x":400,"phase_y":2620.387842638},{"index":38,"phase_x":400,"phase_y":2620.387842638},{"index":39,"phase_x":400,"phase_y":2620.387842638}]